LICENSE
README.md
malleablec2/__init__.py
malleablec2/components.py
malleablec2/grammar.lark
malleablec2/randomizer.py
pymalleablec2-0.1.0.dist-info/LICENSE
pymalleablec2-0.1.0.dist-info/WHEEL
pymalleablec2-0.1.0.dist-info/METADATA
pymalleablec2-0.1.0.dist-info/RECORD
