Metadata-Version: 2.1
Name: pymalleablec2
Version: 0.1.0
Summary: Python library that allows you to parse and build Cobalt Strike Malleable C2 Profiles programmatically.
Home-page: https://github.com/Porchetta-Industries/pyMalleableC2
License: GPL-3.0-only
Author: Marcello Salvati
Author-email: marcello@porchetta.industries
Requires-Python: >=3.6,<4.0
Classifier: License :: OSI Approved :: GNU General Public License v3 (GPLv3)
Classifier: Programming Language :: Python :: 3
Classifier: Programming Language :: Python :: 3.6
Classifier: Programming Language :: Python :: 3.7
Classifier: Programming Language :: Python :: 3.8
Classifier: Programming Language :: Python :: 3.9
Classifier: Topic :: Security
Requires-Dist: lark-parser (>=0.11.1,<0.12.0)
Project-URL: Repository, https://github.com/Porchetta-Industries/pyMalleableC2
